decouple.py
python_decouple_x-3.6.1.dist-info/LICENSE
python_decouple_x-3.6.1.dist-info/METADATA
python_decouple_x-3.6.1.dist-info/WHEEL
python_decouple_x-3.6.1.dist-info/top_level.txt
python_decouple_x-3.6.1.dist-info/RECORD
