Metadata-Version: 2.1
Name: python-decouple-x
Version: 3.6.1
Summary: Strict separation of settings from code.
Home-page: http://github.com/henriquebastos/python-decouple/
Author: Henrique Bastos
Author-email: henrique@bastos.net
License: MIT
Platform: any
Classifier: Development Status :: 5 - Production/Stable
Classifier: Framework :: Django
Classifier: Framework :: Flask
Classifier: Intended Audience :: Developers
Classifier: License :: OSI Approved :: MIT License
Classifier: Natural Language :: English
Classifier: Operating System :: OS Independent
Classifier: Programming Language :: Python
Classifier: Programming Language :: Python :: 3
Classifier: Topic :: Software Development :: Libraries
License-File: LICENSE
Requires-Dist: python-dotenv
Requires-Dist: PyYAML
